{
  "id": "g56g43g38g29g11sent",
  "name": "g56g43g38g29g11sent",
  "parentIds": [
    "g43g38g29g11sentine"
  ],
  "mutationDelta": "a-operand 2→5",
  "instructions": [
    {
      "opcode": "ADD",
      "modifier": "F",
      "a": {
        "mode": "#",
        "value": 0
      },
      "b": {
        "mode": "$",
        "value": 3
      },
      "raw": "ADD.F #0, 3"
    },
    {
      "opcode": "ADD",
      "modifier": "F",
      "a": {
        "mode": "#",
        "value": 4
      },
      "b": {
        "mode": "$",
        "value": 3
      },
      "raw": "ADD.F #4, 3"
    },
    {
      "opcode": "MOV",
      "modifier": "F",
      "a": {
        "mode": "$",
        "value": 5
      },
      "b": {
        "mode": "@",
        "value": 2
      },
      "raw": "MOV.F 5, @2"
    },
    {
      "opcode": "JMP",
      "modifier": "F",
      "a": {
        "mode": "$",
        "value": -2
      },
      "b": {
        "mode": "$",
        "value": -5
      },
      "raw": "JMP.F -2, -5"
    },
    {
      "opcode": "DAT",
      "modifier": "F",
      "a": {
        "mode": "#",
        "value": 0
      },
      "b": {
        "mode": "#",
        "value": 0
      },
      "raw": "DAT.F #0, #0"
    }
  ],
  "start": 0,
  "source": ";name g56g43g38g29g11sent\norg 0\nADD.F #0, 3\nADD.F #4, 3\nMOV.F 5, @2\nJMP.F -2, -5\nDAT.F #0, #0\nend\n",
  "generation": 5,
  "profileId": "kennel94",
  "record": {
    "wins": 4,
    "losses": 1,
    "ties": 3
  },
  "score": 15.18,
  "benchmarkRecord": {
    "wins": 2,
    "losses": 2,
    "ties": 4
  },
  "benchmarkScore": 10.18,
  "displayName": "Static Needle",
  "genomeHash": "99cfe985395caa87",
  "currentLeagueRank": 4,
  "semantic": {
    "schemaVersion": 1,
    "instructionCount": 5,
    "opcodeCounts": {
      "ADD": 2,
      "MOV": 1,
      "JMP": 1,
      "DAT": 1
    },
    "addressingModeCounts": {
      "#": 4,
      "$": 5,
      "@": 1
    },
    "hasSpl": false,
    "backwardBranches": [
      {
        "at": 3,
        "opcode": "JMP",
        "offset": -2,
        "loopLength": 2
      }
    ],
    "fixedArithmeticPointerSteps": [
      {
        "at": 0,
        "opcode": "ADD",
        "step": 0,
        "targetMode": "$",
        "targetOffset": 3
      },
      {
        "at": 1,
        "opcode": "ADD",
        "step": 4,
        "targetMode": "$",
        "targetOffset": 3
      }
    ],
    "genomeHash": "99cfe985395caa87",
    "normalizedGenome": "ADD.F #0,$3\nADD.F #4,$3\nMOV.F $5,@2\nJMP.F $-2,$-5\nDAT.F #0,#0\norg 0",
    "facts": [
      "5 instructions",
      "contains a backward JMP forming a 2-instruction loop",
      "ADD uses fixed immediate step 0",
      "ADD uses fixed immediate step 4"
    ]
  },
  "status": "active",
  "retentionReason": "retained as broad competitor",
  "selectionEvidence": {
    "currentLeagueRecord": {
      "wins": 4,
      "losses": 1,
      "ties": 3
    },
    "benchmarkRecord": {
      "wins": 2,
      "losses": 2,
      "ties": 4
    },
    "currentLeagueRank": 4,
    "summary": "current league record: 4W / 3D / 1L; benchmark record: 2W / 4D / 2L"
  },
  "warriorFacts": {
    "schemaVersion": 1,
    "instructionCount": 5,
    "opcodeCounts": {
      "ADD": 2,
      "MOV": 1,
      "JMP": 1,
      "DAT": 1
    },
    "addressingModeCounts": {
      "#": 4,
      "$": 5,
      "@": 1
    },
    "hasSpl": false,
    "backwardBranches": [
      {
        "at": 3,
        "opcode": "JMP",
        "offset": -2,
        "loopLength": 2
      }
    ],
    "fixedArithmeticPointerSteps": [
      {
        "at": 0,
        "opcode": "ADD",
        "step": 0,
        "targetMode": "$",
        "targetOffset": 3
      },
      {
        "at": 1,
        "opcode": "ADD",
        "step": 4,
        "targetMode": "$",
        "targetOffset": 3
      }
    ],
    "genomeHash": "99cfe985395caa87",
    "normalizedGenome": "ADD.F #0,$3\nADD.F #4,$3\nMOV.F $5,@2\nJMP.F $-2,$-5\nDAT.F #0,#0\norg 0",
    "facts": [
      "5 instructions",
      "contains a backward JMP forming a 2-instruction loop",
      "ADD uses fixed immediate step 0",
      "ADD uses fixed immediate step 4"
    ]
  }
}
